matsimtools/Events.py
matsimtools/Network.py
matsimtools/Plans.py
matsimtools/TripEventHandler.py
matsimtools/__init__.py
matsimtools/calibration.py
matsimtools/utils.py
matsimtools/writers.py
matsimtools/pb/Events_pb2.py
matsimtools/pb/Ids_pb2.py
matsimtools/pb/Model_pb2.py
matsimtools/pb/Wireformat_pb2.py
matsimtools_ifpen-0.0.13.dist-info/METADATA
matsimtools_ifpen-0.0.13.dist-info/WHEEL
matsimtools_ifpen-0.0.13.dist-info/top_level.txt
matsimtools_ifpen-0.0.13.dist-info/RECORD
