Metadata-Version: 2.1
Name: matsimtools-ifpen
Version: 0.0.13
Summary: MATSim Agent-Based Transportation Simulation Framework - official python analysis tools
Home-page: https://github.com/matsim-vsp/matsim-python-tools
Author: VSP-Berlin
Author-email: charlton@tu-berlin.de
License: GPLv3
Classifier: License :: OSI Approved :: GNU General Public License (GPL)
Classifier: Programming Language :: Python :: 3
Requires-Dist: protobuf (>=3.10.0)
Requires-Dist: xopen
Requires-Dist: pandas
Provides-Extra: calibration
Requires-Dist: optuna (>=2.7.0) ; extra == 'calibration'
